MANIFEST.in
README.md
README.rst
setup.cfg
setup.py
bin/cvutils-crop
bin/cvutils-resize
cvutils/__init__.py
cvutils/cvhighgui.py
cvutils/cvimgproc.py
cvutils/cvos.py
cvutils.egg-info/PKG-INFO
cvutils.egg-info/SOURCES.txt
cvutils.egg-info/dependency_links.txt
cvutils.egg-info/not-zip-safe
cvutils.egg-info/requires.txt
cvutils.egg-info/top_level.txt