Metadata-Version: 1.1
Name: cvutils
Version: 0.2.4
Summary: Utilites for Computer Vision and Image Processing
Home-page: http://github.com/bikz05/bikz05/cvutils
Author: Bikramjot Singh Hanzra
Author-email: bikz.05@gmail.com
License: MIT
Download-URL: https://github.com/bikz05/cvutils/archive/0.2.4
Keywords: computer vision,image procesing
Platform: UNKNOWN
